pybmoore/__init__.py
pybmoore/_bm.c
pybmoore/_bm.cpython-312-aarch64-linux-gnu.so
pybmoore/_boyer_moore.py
pybmoore-2.2.0.dist-info/METADATA
pybmoore-2.2.0.dist-info/WHEEL
pybmoore-2.2.0.dist-info/top_level.txt
pybmoore-2.2.0.dist-info/RECORD
pybmoore-2.2.0.dist-info/licenses/LICENSE
