Metadata-Version: 2.4
Name: pybmoore
Version: 2.2.0
Summary: Python/Cython implementation of Boyer-Moore string-search algorithm
Author-email: Alexandre Menezes <alexandre.fmenezes@gmail.com>
License-Expression: Apache-2.0
Project-URL: Documentation, https://github.com/amenezes/pybmoore
Project-URL: Code, https://github.com/amenezes/pybmoore
Project-URL: Issue-tracker, https://github.com/amenezes/pybmoore/issues
Project-URL: Changes, https://github.com/amenezes/pybmoore/releases
Keywords: search,boyer-moore,text-search
Classifier: Development Status :: 5 - Production/Stable
Classifier: Intended Audience :: Developers
Classifier: Operating System :: OS Independent
Classifier: Programming Language :: Python
Classifier: Programming Language :: Cython
Classifier: Programming Language :: Python :: 3 :: Only
Classifier: Programming Language :: Python :: 3.10
Classifier: Programming Language :: Python :: 3.11
Classifier: Programming Language :: Python :: 3.12
Classifier: Programming Language :: Python :: 3.13
Classifier: Programming Language :: Python :: Implementation :: CPython
Classifier: Programming Language :: Python :: Implementation :: PyPy
Classifier: Topic :: Software Development :: Libraries
Classifier: Topic :: Software Development :: Libraries :: Python Modules
Requires-Python: >=3.10
License-File: LICENSE
Provides-Extra: dev
Requires-Dist: mypy; extra == "dev"
Requires-Dist: ruff; extra == "dev"
Requires-Dist: pytest; extra == "dev"
Requires-Dist: pytest-cov; extra == "dev"
Requires-Dist: coverage; extra == "dev"
Requires-Dist: pytest-asyncio; extra == "dev"
Requires-Dist: pre-commit; extra == "dev"
Requires-Dist: radon; extra == "dev"
Requires-Dist: bandit; extra == "dev"
Provides-Extra: docs
Requires-Dist: mkdocs-material; extra == "docs"
Provides-Extra: benchmark
Requires-Dist: pytest-benchmark; extra == "benchmark"
Provides-Extra: all
Requires-Dist: mkdocs-material; extra == "all"
Requires-Dist: pytest-benchmark; extra == "all"
Dynamic: license-file
